cdmetro
