Metadata-Version: 1.1
Name: cdmetro
Version: 1.0.12
Summary: Un admin de django diferente
Home-page: https://github.com/UnTalDulcey/cdmetro
Author: Cristian Dulcey - Emiraldo Lozano
Author-email: christian.dulcey@gmail.com
License: MIT
Keywords: sample setuptools development
Platform: UNKNOWN
Classifier: Development Status :: 3 - Alpha
Classifier: Intended Audience :: Developers
Classifier: Topic :: Software Development :: Build Tools
Classifier: License :: OSI Approved :: MIT License
Classifier: Programming Language :: Python :: 2.7
